LICENSE.txt
setup.cfg
setup.py
attemptGZ/Package.py
attemptGZ/__init__.py
attemptGZ.egg-info/PKG-INFO
attemptGZ.egg-info/SOURCES.txt
attemptGZ.egg-info/dependency_links.txt
attemptGZ.egg-info/requires.txt
attemptGZ.egg-info/top_level.txt
attemptGZ/IMAGES/100008.jpg
attemptGZ/IMAGES/100023.jpg
attemptGZ/IMAGES/100053.jpg
attemptGZ/IMAGES/100078.jpg
attemptGZ/IMAGES/100090.jpg
attemptGZ/IMAGES/100122.jpg
attemptGZ/IMAGES/100123.jpg
attemptGZ/IMAGES/100128.jpg
attemptGZ/IMAGES/100134.jpg
attemptGZ/IMAGES/100143.jpg
attemptGZ/IMAGES/100150.jpg
attemptGZ/IMAGES/100157.jpg
attemptGZ/IMAGES/100204.jpg
attemptGZ/IMAGES/100237.jpg
attemptGZ/IMAGES/100259.jpg
attemptGZ/IMAGES/100263.jpg
attemptGZ/IMAGES/100288.jpg
attemptGZ/IMAGES/100295.jpg
attemptGZ/IMAGES/100322.jpg
attemptGZ/IMAGES/100335.jpg
attemptGZ/IMAGES/100380.jpg
attemptGZ/IMAGES/100382.jpg
attemptGZ/IMAGES/100383.jpg
attemptGZ/IMAGES/100402.jpg
attemptGZ/IMAGES/100428.jpg
attemptGZ/IMAGES/100434.jpg
attemptGZ/IMAGES/100444.jpg
attemptGZ/IMAGES/100445.jpg
attemptGZ/IMAGES/100458.jpg
attemptGZ/IMAGES/100474.jpg
attemptGZ/IMAGES/100479.jpg
attemptGZ/IMAGES/100506.jpg
attemptGZ/IMAGES/100513.jpg
attemptGZ/IMAGES/100520.jpg
attemptGZ/IMAGES/100541.jpg
attemptGZ/IMAGES/100561.jpg
attemptGZ/IMAGES/100571.jpg
attemptGZ/IMAGES/100601.jpg
attemptGZ/IMAGES/100623.jpg
attemptGZ/IMAGES/100672.jpg
attemptGZ/IMAGES/100673.jpg
attemptGZ/IMAGES/100724.jpg
attemptGZ/IMAGES/100727.jpg
attemptGZ/IMAGES/100730.jpg
attemptGZ/IMAGES/100740.jpg
attemptGZ/IMAGES/100744.jpg
attemptGZ/IMAGES/100765.jpg
attemptGZ/IMAGES/100774.jpg
attemptGZ/IMAGES/100801.jpg
attemptGZ/IMAGES/100813.jpg
attemptGZ/IMAGES/100821.jpg
attemptGZ/IMAGES/100822.jpg
attemptGZ/IMAGES/100836.jpg
attemptGZ/IMAGES/100852.jpg
attemptGZ/IMAGES/100859.jpg
attemptGZ/IMAGES/100861.jpg
attemptGZ/IMAGES/100867.jpg
attemptGZ/IMAGES/100887.jpg
attemptGZ/IMAGES/100894.jpg
attemptGZ/IMAGES/100938.jpg
attemptGZ/IMAGES/100951.jpg
attemptGZ/IMAGES/100986.jpg
attemptGZ/IMAGES/101007.jpg
attemptGZ/IMAGES/101061.jpg
attemptGZ/IMAGES/101074.jpg
attemptGZ/IMAGES/101092.jpg
attemptGZ/IMAGES/101127.jpg
attemptGZ/IMAGES/101133.jpg
